dojinvoice_db/__init__.py
dojinvoice_db/database.py
dojinvoice_db/download.py
dojinvoice_db/main.py
dojinvoice_db/parser.py
dojinvoice_db/py.typed
dojinvoice_db-2.1.0.dist-info/METADATA
dojinvoice_db-2.1.0.dist-info/WHEEL
dojinvoice_db-2.1.0.dist-info/entry_points.txt
dojinvoice_db-2.1.0.dist-info/licenses/LICENSE
dojinvoice_db-2.1.0.dist-info/RECORD
