Metadata-Version: 2.4
Name: dojinvoice-db
Version: 2.1.0
Summary: Make DB of Dojinvoice
Project-URL: Repository, https://github.com/eggplants/dojinvoice_db
Author-email: eggplants <w10776e8w@yahoo.co.jp>
License: MIT
License-File: LICENSE
Keywords: dlsite,selenium
Classifier: Development Status :: 3 - Alpha
Classifier: License :: OSI Approved :: MIT License
Classifier: Programming Language :: Python :: 3 :: Only
Classifier: Programming Language :: Python :: 3.12
Classifier: Programming Language :: Python :: 3.13
Classifier: Programming Language :: Python :: 3.14
Classifier: Programming Language :: Python :: Implementation :: CPython
Classifier: Typing :: Typed
Requires-Python: <4,>=3.12
Requires-Dist: beautifulsoup4<5,>=4.12.3
Requires-Dist: humanfriendly<11,>=10
Requires-Dist: install-playwright<1.1,>=0.1
Requires-Dist: lxml<7,>=5.3
Requires-Dist: playwright<2,>=1.49.1
Requires-Dist: requests<3,>=2.32.3
Requires-Dist: types-beautifulsoup4<5,>=4.12.0.20241020
Requires-Dist: types-humanfriendly<11,>=10.0.1.20241221
Requires-Dist: types-requests<3,>=2.32.0.20241016
